finazon/__init__.py
finazon/base.py
finazon/benzinga.py
finazon/core.py
finazon/markets.py
finazon/sip.py
finazon/tickers.py
finazon/utils.py
tests/__init__.py
tests/test_core.py
pyFinazon-0.1.dist-info/METADATA
pyFinazon-0.1.dist-info/WHEEL
pyFinazon-0.1.dist-info/top_level.txt
pyFinazon-0.1.dist-info/RECORD
