Metadata-Version: 2.1
Name: pyFinazon
Version: 0.1
Summary: finazon wrapper
Home-page: https://github.com/bossdown123/pyFinazon
Author: Adam
Author-email: adamvibeo@gmail.com
Classifier: Programming Language :: Python :: 3
Classifier: License :: OSI Approved :: MIT License
Requires-Dist: requests
Requires-Dist: datetime
Requires-Dist: pandas
